odoo/addons/stock_picking_product_label/README.rst
odoo/addons/stock_picking_product_label/__init__.py
odoo/addons/stock_picking_product_label/__manifest__.py
odoo/addons/stock_picking_product_label/i18n/sl.po
odoo/addons/stock_picking_product_label/i18n/stock_picking_product_label.pot
odoo/addons/stock_picking_product_label/readme/CONTRIBUTORS.rst
odoo/addons/stock_picking_product_label/readme/DESCRIPTION.rst
odoo/addons/stock_picking_product_label/readme/USAGE.rst
odoo/addons/stock_picking_product_label/reports/report_print_labels.xml
odoo/addons/stock_picking_product_label/reports/report_print_labels_template.xml
odoo/addons/stock_picking_product_label/static/description/icon.png
odoo/addons/stock_picking_product_label/static/description/index.html
odoo12_addon_stock_picking_product_label-12.0.1.0.0.99.dev7.dist-info/METADATA
odoo12_addon_stock_picking_product_label-12.0.1.0.0.99.dev7.dist-info/WHEEL
odoo12_addon_stock_picking_product_label-12.0.1.0.0.99.dev7.dist-info/top_level.txt
odoo12_addon_stock_picking_product_label-12.0.1.0.0.99.dev7.dist-info/RECORD
